mails/__init__.py
mails/skeleton.py
mails-0.0.1.dist-info/DESCRIPTION.rst
mails-0.0.1.dist-info/METADATA
mails-0.0.1.dist-info/RECORD
mails-0.0.1.dist-info/WHEEL
mails-0.0.1.dist-info/metadata.json
mails-0.0.1.dist-info/top_level.txt
